{
  "indexes": [
    {
      "collectionGroup": "tasks",
      "queryScope": "COLLECTION",
      "fields": [
        { "fieldPath": "visibility", "order": "ASCENDING" },
        { "fieldPath": "status", "order": "ASCENDING" }
      ]
    },
    {
      "collectionGroup": "bids",
      "queryScope": "COLLECTION",
      "fields": [
        { "fieldPath": "taskId", "order": "ASCENDING" },
        { "fieldPath": "bidderId", "order": "ASCENDING" }
      ]
    },
    {
      "collectionGroup": "wallet_txs",
      "queryScope": "COLLECTION",
      "fields": [
        { "fieldPath": "userId", "order": "ASCENDING" },
        { "fieldPath": "createdAt", "order": "DESCENDING" }
      ]
    }
  ],
  "fieldOverrides": []
}
